{
    "key": "group_61b36ea4931f5",
    "title": "Kategoria kuligów",
    "fields": [
        {
            "key": "field_61b36ed2f6eca",
            "label": "Zdjęcie kategorii",
            "name": "kulcat_image",
            "type": "image",
            "instructions": "",
            "required": 1,
            "conditional_logic": 0,
            "wrapper": {
                "width": "",
                "class": "",
                "id": ""
            },
            "return_format": "url",
            "preview_size": "medium",
            "library": "all",
            "min_width": "",
            "min_height": "",
            "min_size": "",
            "max_width": "",
            "max_height": "",
            "max_size": "",
            "mime_types": ""
        },
        {
            "key": "field_61b37229ea401",
            "label": "Ikona",
            "name": "kulcat_flag_ico",
            "type": "image",
            "instructions": "",
            "required": 1,
            "conditional_logic": 0,
            "wrapper": {
                "width": "30",
                "class": "",
                "id": ""
            },
            "return_format": "url",
            "preview_size": "medium",
            "library": "all",
            "min_width": "",
            "min_height": "",
            "min_size": "",
            "max_width": "",
            "max_height": "",
            "max_size": "",
            "mime_types": ""
        },
        {
            "key": "field_61b3723bea402",
            "label": "Tekst",
            "name": "kulcat_flag_text",
            "type": "text",
            "instructions": "",
            "required": 1,
            "conditional_logic": 0,
            "wrapper": {
                "width": "70",
                "class": "",
                "id": ""
            },
            "default_value": "",
            "placeholder": "",
            "prepend": "",
            "append": "",
            "maxlength": ""
        },
        {
            "key": "field_61b37285d5ccd",
            "label": "Liczba opinii",
            "name": "kulcat_reviews",
            "type": "number",
            "instructions": "",
            "required": 1,
            "conditional_logic": 0,
            "wrapper": {
                "width": "",
                "class": "",
                "id": ""
            },
            "default_value": "",
            "placeholder": "",
            "prepend": "",
            "append": "",
            "min": "",
            "max": "",
            "step": ""
        },
        {
            "key": "field_61b37295d5cce",
            "label": "USP",
            "name": "kulcat_usp",
            "type": "repeater",
            "instructions": "",
            "required": 0,
            "conditional_logic": 0,
            "wrapper": {
                "width": "",
                "class": "",
                "id": ""
            },
            "collapsed": "",
            "min": 0,
            "max": 0,
            "layout": "table",
            "button_label": "",
            "sub_fields": [
                {
                    "key": "field_61b372c7d5cd0",
                    "label": "Ikona",
                    "name": "kulcat_usp_ico",
                    "type": "image",
                    "instructions": "",
                    "required": 1,
                    "conditional_logic": 0,
                    "wrapper": {
                        "width": "30",
                        "class": "",
                        "id": ""
                    },
                    "return_format": "url",
                    "preview_size": "medium",
                    "library": "all",
                    "min_width": "",
                    "min_height": "",
                    "min_size": "",
                    "max_width": "",
                    "max_height": "",
                    "max_size": "",
                    "mime_types": ""
                },
                {
                    "key": "field_61b372bfd5ccf",
                    "label": "Tekst",
                    "name": "kulcat_usp_text",
                    "type": "text",
                    "instructions": "",
                    "required": 1,
                    "conditional_logic": 0,
                    "wrapper": {
                        "width": "70",
                        "class": "",
                        "id": ""
                    },
                    "default_value": "",
                    "placeholder": "",
                    "prepend": "",
                    "append": "",
                    "maxlength": ""
                }
            ]
        }
    ],
    "location": [
        [
            {
                "param": "taxonomy",
                "operator": "==",
                "value": "kategorie_kuligi"
            }
        ]
    ],
    "menu_order": 0,
    "position": "normal",
    "style": "default",
    "label_placement": "top",
    "instruction_placement": "label",
    "hide_on_screen": "",
    "active": true,
    "description": "",
    "modified": 1640087295
}